prjforinfcreditvilfw/__init__.py
prjforinfcreditvilfw/analyze/__init__.py
prjforinfcreditvilfw/analyze/analyzeequi.py
prjforinfcreditvilfw/analyze/analyzesolu.py
prjforinfcreditvilfw/analyze/analyzesteady.py
prjforinfcreditvilfw/analyze/csvcheck/__init__.py
prjforinfcreditvilfw/analyze/csvcheck/check_soluj7.py
prjforinfcreditvilfw/boto3aws/__init__.py
prjforinfcreditvilfw/boto3aws/aws_batch/__init__.py
prjforinfcreditvilfw/boto3aws/aws_batch/gen_batch_job.py
prjforinfcreditvilfw/boto3aws/aws_batch/README.md
prjforinfcreditvilfw/boto3aws/aws_batch/sandbox_batch_register.py
prjforinfcreditvilfw/boto3aws/aws_batch/sandbox_batch_submit.py
prjforinfcreditvilfw/boto3aws/aws_batch/submit_batch_job.py
prjforinfcreditvilfw/boto3aws/aws_ec2/__init__.py
prjforinfcreditvilfw/boto3aws/aws_ec2/ec2_manage.py
prjforinfcreditvilfw/boto3aws/aws_ec2/pem/ami20140410.pem
prjforinfcreditvilfw/boto3aws/aws_ec2/pem/ami20140410.ppk
prjforinfcreditvilfw/boto3aws/aws_ec2/pem/amibasic.pem
prjforinfcreditvilfw/boto3aws/aws_ec2/pem/amibasic.ppk
prjforinfcreditvilfw/boto3aws/aws_ec2/pem/anacondaSep2015.pem
prjforinfcreditvilfw/boto3aws/aws_ec2/pem/anacondaSep2015.ppk
prjforinfcreditvilfw/boto3aws/aws_ec2/pem/fan_wang-key-pair-us_east_nv.pem
prjforinfcreditvilfw/boto3aws/aws_ec2/pem/fan_wang-key-pair-us_east_nv.ppk
prjforinfcreditvilfw/boto3aws/aws_ec2/pem/rdyfeivmar17-key-pair-ohio.pem
prjforinfcreditvilfw/boto3aws/aws_ec2/pem/rdyfeivmar17-key-pair-ohio.ppk
prjforinfcreditvilfw/boto3aws/aws_ec2/pem/README.md
prjforinfcreditvilfw/boto3aws/aws_ec2/README.md
prjforinfcreditvilfw/boto3aws/aws_ecr/__init__.py
prjforinfcreditvilfw/boto3aws/aws_ecr/container/__init__.py
prjforinfcreditvilfw/boto3aws/aws_ecr/container/DockerfileConda
prjforinfcreditvilfw/boto3aws/aws_ecr/container/DockerfileCondaOld
prjforinfcreditvilfw/boto3aws/aws_ecr/container/DockerfileCondaPyFan
prjforinfcreditvilfw/boto3aws/aws_ecr/container/DockerfileInstall
prjforinfcreditvilfw/boto3aws/aws_ecr/container/DockerfileMiniconda
prjforinfcreditvilfw-0.1.2.dist-info/WHEEL
prjforinfcreditvilfw-0.1.2.dist-info/METADATA
prjforinfcreditvilfw-0.1.2.dist-info/RECORD
