Metadata-Version: 2.1
Name: prjforinfcreditvilfw
Version: 0.1.2
Summary: 
Author: Fan Wang
Author-email: wangfanbsg75@live.com
Requires-Python: >=3.8,<4.0
Classifier: Programming Language :: Python :: 3
Classifier: Programming Language :: Python :: 3.8
Classifier: Programming Language :: Python :: 3.9
Requires-Dist: boto3 (>=1.15.18,<2.0.0)
Requires-Dist: cryptography (>=3.0.0,<4.0.0)
Requires-Dist: cython (>=0.29.20,<0.30.0)
Requires-Dist: interpolation (>=2.0.0,<3.0.0)
Requires-Dist: matplotlib (>=3.2.1,<4.0.0)
Requires-Dist: numba (>=0.50.1,<0.51.0)
Requires-Dist: numpy (>=1.18.5,<2.0.0)
Requires-Dist: pyfan (>=0.1.0,<0.2.0)
Requires-Dist: python-frontmatter (>=0.5.0,<0.6.0)
Requires-Dist: pyyaml (>=5.3.1,<6.0.0)
Requires-Dist: scipy (>=1.4.1,<2.0.0)
Requires-Dist: seaborn (>=0.10.1,<0.11.0)
Requires-Dist: sklearn (>=0.0,<0.1)
Requires-Dist: statsmodels (>=0.11.1,<0.12.0)
Requires-Dist: urllib3 (>=1.25.10,<2.0.0)
